{
  "predicted_class": "self-deprecating",
  "confidence_score": 0.9339222311973572,
  "class_probabilities": "{\"self-enhancing\": 0.04657193645834923, \"self-deprecating\": 0.9339222311973572, \"affiliative\": 0.009567754343152046, \"aggressive\": 0.00940961204469204, \"neutral\": 0.0005285217193886638}",
  "top_features": "{\"my\": 0.6115338109980318, \"consequences\": 0.1842373578662667, \"actions\": 0.15886704986385966, \"If\": 0.12136115785191755, \"questionable\": 0.06931956303950972}",
  "primary_emotion": "anger   : 0.862",
  "emotion_distribution": "[\"  anger   : 0.862\", \"  fear    : 0.093\", \"  sadness : 0.033\", \"  joy     : 0.010\", \"  surprise: 0.001\", \"  love    : 0.001\"]",
  "dominant_sentiment": "NEGATIVE",
  "sentiment_confidence": 0.9987284541130066,
  "sentiment_polarity": -0.5,
  "sentiment_subjectivity": 1.0,
  "sarcasm_probability": 0.0,
  "is_sarcastic": 0,
  "has_contrast": 0,
  "exaggeration_count": 0,
  "intensifier_count": 0,
  "semantic_conflict_count": 9,
  "rhyme_count": 1,
  "has_alliteration": 1,
  "self_reference_count": 1,
  "pun_count": 0,
  "syllable_complexity": 1.21,
  "homonym_count": 6,
  "linguistic_details": "{\"rhymes\": {\"count\": 1, \"pairs\": [[\"we\", \"t\"]], \"found\": true}, \"alliteration\": {\"found\": true, \"groups\": {\"W\": [\"well\", \"we\"], \"HH\": [\"who\", \"have\", \"here\"], \"IH1\": [\"if\", \"it\", \"is\"], \"K\": [\"consequences\", \"questionable\"]}}, \"puns\": {\"count\": 0, \"pairs\": [], \"found\": false}, \"syllables\": {\"total\": 23, \"average\": 1.21, \"by_word\": {\"Well\": 1, \",\": 1, \"look\": 1, \"who\": 1, \"we\": 1, \"have\": 1, \"here\": 1, \".\": 1, \"If\": 1, \"it\": 1, \"isn\": 1, \"\\u2019\": 1, \"t\": 1, \"the\": 1, \"consequences\": 2, \"of\": 1, \"my\": 1, \"questionable\": 3, \"actions\": 2}}, \"homonyms\": {\"count\": 6, \"words\": {\"who\": [\"hoo\"], \"we\": [\"whee\", \"wee\"], \"have\": [\"halve\"], \"here\": [\"hear\"], \"t\": [\"ti\", \"tee\", \"tea\"], \"the\": [\"thee\"]}, \"found\": true}, \"self_reference\": {\"count\": 1, \"instances\": [[\"my\", \"questionable\"]], \"found\": true}, \"pos_distribution\": {\"IN\": 3, \"VBZ\": 1, \"DT\": 1, \"PRP$\": 1, \"JJ\": 2, \"PRP\": 2, \"WP\": 1, \"NNS\": 2, \"NN\": 1, \"VBP\": 1, \"RB\": 2}}",
  "detailed_analysis": "{\"linguistic_full\": {\"rhyme_pairs\": [[\"we\", \"t\"]], \"alliteration\": {\"W\": [\"well\", \"we\"], \"HH\": [\"who\", \"have\", \"here\"], \"IH1\": [\"if\", \"it\", \"is\"], \"K\": [\"consequences\", \"questionable\"]}, \"puns\": [], \"homonyms\": {\"who\": [\"hoo\"], \"we\": [\"whee\", \"wee\"], \"have\": [\"halve\"], \"here\": [\"hear\"], \"t\": [\"ti\", \"tee\", \"tea\"], \"the\": [\"thee\"]}, \"syllable_count\": {\"Well\": 1, \",\": 1, \"look\": 1, \"who\": 1, \"we\": 1, \"have\": 1, \"here\": 1, \".\": 1, \"If\": 1, \"it\": 1, \"isn\": 1, \"\\u2019\": 1, \"t\": 1, \"the\": 1, \"consequences\": 2, \"of\": 1, \"my\": 1, \"questionable\": 3, \"actions\": 2}, \"self_reference\": [1, [[\"my\", \"questionable\"]]], \"synset_wordnet\": {\"Well\": \"{'advantageously', 'good', 'considerably', 'comfortably', 'well', 'substantially', 'fountainhead', 'wellspring', 'swell', 'intimately', 'easily'}\", \"look\": \"{'face', 'smell', 'front', 'wait', 'spirit', 'reckon', 'take_care', 'see', 'look', 'feeling', 'expect', 'bet', 'aspect', 'looking', 'seem', 'expression', 'attend', 'depend', 'feel', 'count', 'calculate', 'flavour', 'appear', 'await', 'facial_expression', 'tone', 'search', 'looking_at', 'flavor'}\", \"who\": \"{'WHO', 'World_Health_Organization'}\", \"we\": \"set()\", \"have\": \"{'get', 'sustain', 'have', 'suffer', 'take_in', 'give_birth', 'cause', 'possess', 'bear', 'have_got', 'feature', 'throw', 'birth', 'stimulate', 'accept', 'experience', 'let', 'deliver', 'rich_person', 'wealthy_person', 'take', 'own', 'make', 'receive', 'hold', 'ingest', 'give', 'consume', 'induce'}\", \"here\": \"{'Hera', 'hither', 'here', 'Here'}\", \"If\": \"set()\", \"it\": \"{'information_technology', 'IT'}\", \"isn\": \"{'International_Relations_and_Security_Network', 'ISN'}\", \"\\u2019\": \"set()\", \"t\": \"{'t', 'MT', 'T', 'tonne', 'liothyronine', 'thymine', 'thyroxine', 'thyroxin', 'tetraiodothyronine', 'metric_ton', 'deoxythymidine_monophosphate', 'triiodothyronine'}\", \"the\": \"set()\", \"consequences\": \"{'issue', 'outcome', 'import', 'event', 'result', 'upshot', 'consequence', 'aftermath', 'moment', 'effect'}\", \"of\": \"set()\", \"my\": \"set()\", \"questionable\": \"{'confutable', 'confutative', 'questionable', 'refutable'}\", \"actions\": \"{'fulfil', 'action_mechanism', 'execute', 'military_action', 'natural_action', 'natural_process', 'sue', 'action_at_law', 'legal_action', 'process', 'activity', 'carry_through', 'activeness', 'carry_out', 'fulfill', 'accomplish', 'litigate', 'action'}\"}, \"part_of_speech\": [[\"Well\", \"RB\"], [\"look\", \"NN\"], [\"who\", \"WP\"], [\"we\", \"PRP\"], [\"have\", \"VBP\"], [\"here\", \"RB\"], [\"If\", \"IN\"], [\"it\", \"PRP\"], [\"isn\", \"VBZ\"], [\"\\u2019\", \"JJ\"], [\"t\", \"IN\"], [\"the\", \"DT\"], [\"consequences\", \"NNS\"], [\"of\", \"IN\"], [\"my\", \"PRP$\"], [\"questionable\", \"JJ\"], [\"actions\", \"NNS\"]]}, \"semantic_full\": {\"sentence_contrast\": [], \"word_sentiment\": {\"Well\": 0.322, \"look\": 0.008928571428571428, \"have\": -0.03125, \"here\": 0.0, \"isn\": 0.0, \"consequences\": 0.08333333333333333, \"questionable\": 0.0, \"actions\": 0.041666666666666664}, \"exaggerations\": [], \"intensifiers\": [], \"semantic_conflicts\": [[\"Well\", \"isn\"], [\"look\", \"isn\"], [\"have\", \"isn\"], [\"here\", \"isn\"], [\"isn\", \"consequences\"], [\"isn\", \"questionable\"], [\"isn\", \"actions\"], [\"consequences\", \"questionable\"], [\"questionable\", \"actions\"]]}, \"sentiment_full\": {\"dominant_sentiment\": {\"label\": \"NEGATIVE\", \"confidence\": 0.9987284541130066}, \"all_sentiments\": {\"NEGATIVE\": 0.999, \"POSITIVE\": 0.001}, \"sentiment_metrics\": {\"polarity\": -0.5, \"strength\": 0.997, \"subjectivity\": 1.0, \"objectivity\": 0.0, \"direction\": \"negative\"}}, \"emotion_full\": [\"  anger   : 0.862\", \"  fear    : 0.093\", \"  sadness : 0.033\", \"  joy     : 0.010\", \"  surprise: 0.001\", \"  love    : 0.001\"], \"sarcasm_full\": {\"sarcasm_probability\": 0.0, \"is_sarcastic\": false}}",
  "humor_mechanisms": "[[\"rhyme\", 1], [\"alliteration\", 4], [\"self_reference\", 1], [\"homonyms\", 6]]",
  "target_analysis": "{\"self_targeted\": true, \"other_targeted\": false, \"situation_targeted\": false}",
  "linguistic_complexity": "{\"sentence_length\": 19, \"unique_words\": 18, \"avg_word_length\": 3.736842105263158, \"grammar_complexity\": 1}",
  "Unnamed: 0": 40,
  "joke": "Well, look who we have here. If it isn\u2019t the consequences of my questionable actions.",
  "label": 1
}