{
  "predicted_class": "neutral",
  "confidence_score": 0.9110173583030701,
  "class_probabilities": "{\"self-enhancing\": 0.018494518473744392, \"self-deprecating\": 0.051472388207912445, \"affiliative\": 0.0107856635004282, \"aggressive\": 0.008230041712522507, \"neutral\": 0.9110173583030701}",
  "top_features": "{\"risk\": 0.04405773789594709, \"4\": -0.04187487799647556, \"become\": -0.034907987551072495, \"a\": 0.02640092831938495, \"taker\": 0.02450268231875257}",
  "primary_emotion": "joy     : 0.818",
  "emotion_distribution": "[\"  joy     : 0.818\", \"  anger   : 0.090\", \"  sadness : 0.057\", \"  fear    : 0.027\", \"  love    : 0.005\", \"  surprise: 0.003\"]",
  "dominant_sentiment": "POSITIVE",
  "sentiment_confidence": 0.9977883100509644,
  "sentiment_polarity": 0.5,
  "sentiment_subjectivity": 0.5,
  "sarcasm_probability": 1.0,
  "is_sarcastic": 1,
  "has_contrast": 0,
  "exaggeration_count": 0,
  "intensifier_count": 0,
  "semantic_conflict_count": 2,
  "rhyme_count": 0,
  "has_alliteration": 1,
  "self_reference_count": 0,
  "pun_count": 0,
  "syllable_complexity": 1.25,
  "homonym_count": 4,
  "linguistic_details": "{\"rhymes\": {\"count\": 0, \"pairs\": [], \"found\": false}, \"alliteration\": {\"found\": true, \"groups\": {\"T\": [\"to\", \"taker\"], \"B\": [\"become\", \"better\"]}}, \"puns\": {\"count\": 0, \"pairs\": [], \"found\": false}, \"syllables\": {\"total\": 10, \"average\": 1.25, \"by_word\": {\"4\": 1, \"ways\": 1, \"to\": 1, \"become\": 2, \"a\": 1, \"better\": 2, \"risk\": 1, \"taker\": 1}}, \"homonyms\": {\"count\": 4, \"words\": {\"ways\": [\"weighs\"], \"to\": [\"two\", \"too\"], \"a\": [\"uh\", \"eh\"], \"better\": [\"bettor\"]}, \"found\": true}, \"self_reference\": {\"count\": 0, \"instances\": [], \"found\": false}, \"pos_distribution\": {\"NNS\": 1, \"CD\": 1, \"NN\": 2, \"VB\": 1, \"DT\": 1, \"JJR\": 1, \"TO\": 1}}",
  "detailed_analysis": "{\"linguistic_full\": {\"rhyme_pairs\": [], \"alliteration\": {\"T\": [\"to\", \"taker\"], \"B\": [\"become\", \"better\"]}, \"puns\": [], \"homonyms\": {\"ways\": [\"weighs\"], \"to\": [\"two\", \"too\"], \"a\": [\"uh\", \"eh\"], \"better\": [\"bettor\"]}, \"syllable_count\": {\"4\": 1, \"ways\": 1, \"to\": 1, \"become\": 2, \"a\": 1, \"better\": 2, \"risk\": 1, \"taker\": 1}, \"self_reference\": [0, []], \"synset_wordnet\": {\"4\": \"{'quaternion', 'quaternary', 'iv', 'four', 'quartet', 'IV', 'Little_Joe', 'tetrad', '4', 'quatern', 'foursome', 'quadruplet', 'quaternity'}\", \"ways\": \"{'ways', 'manner', 'fashion', 'agency', 'room', 'path', 'style', 'direction', 'shipway', 'slipway', 'way', 'elbow_room', 'means', 'way_of_life', 'mode'}\", \"to\": \"set()\", \"become\": \"{'get', 'suit', 'turn', 'go', 'become'}\", \"a\": \"{'axerophthol', 'A', 'a', 'deoxyadenosine_monophosphate', 'ampere', 'antiophthalmic_factor', 'amp', 'adenine', 'angstrom_unit', 'group_A', 'angstrom', 'type_A', 'vitamin_A'}\", \"better\": \"{'ripe', 'right', 'best', 'sound', 'secure', 'amend', 'in_force', 'considerably', 'intimately', 'easily', 'effective', 'ameliorate', 'beneficial', 'practiced', 'just', 'in_effect', 'improve', 'honest', 'advantageously', 'well', 'expert', 'safe', 'salutary', 'meliorate', 'skilful', 'substantially', 'unspoiled', 'adept', 'bettor', 'serious', 'dear', 'upright', 'proficient', 'unspoilt', 'good', 'undecomposed', 'honorable', 'dependable', 'comfortably', 'break', 'better', 'punter', 'estimable', 'respectable', 'skillful', 'full', 'near', 'wagerer'}\", \"risk\": \"{'take_a_chance', 'gamble', 'risk_of_exposure', 'peril', 'adventure', 'risk_of_infection', 'hazard', 'jeopardy', 'take_chances', 'chance', 'run_a_risk', 'risk', 'lay_on_the_line', 'danger', 'endangerment', 'put_on_the_line'}\", \"taker\": \"{'taker'}\"}, \"part_of_speech\": [[\"4\", \"CD\"], [\"ways\", \"NNS\"], [\"to\", \"TO\"], [\"become\", \"VB\"], [\"a\", \"DT\"], [\"better\", \"JJR\"], [\"risk\", \"NN\"], [\"taker\", \"NN\"]]}, \"semantic_full\": {\"sentence_contrast\": [], \"word_sentiment\": {\"ways\": 0.009615384615384616, \"become\": 0.03125, \"better\": 0.52918, \"risk\": -0.08333333333333333, \"taker\": 0.0}, \"exaggerations\": [], \"intensifiers\": [], \"semantic_conflicts\": [[\"ways\", \"become\"], [\"become\", \"taker\"]]}, \"sentiment_full\": {\"dominant_sentiment\": {\"label\": \"POSITIVE\", \"confidence\": 0.9977883100509644}, \"all_sentiments\": {\"NEGATIVE\": 0.002, \"POSITIVE\": 0.998}, \"sentiment_metrics\": {\"polarity\": 0.5, \"strength\": 0.996, \"subjectivity\": 0.5, \"objectivity\": 0.5, \"direction\": \"positive\"}}, \"emotion_full\": [\"  joy     : 0.818\", \"  anger   : 0.090\", \"  sadness : 0.057\", \"  fear    : 0.027\", \"  love    : 0.005\", \"  surprise: 0.003\"], \"sarcasm_full\": {\"sarcasm_probability\": 1.0, \"is_sarcastic\": true}}",
  "humor_mechanisms": "[[\"alliteration\", 2], [\"homonyms\", 4], [\"sarcasm\", 1.0]]",
  "target_analysis": "{\"self_targeted\": false, \"other_targeted\": false, \"situation_targeted\": true}",
  "linguistic_complexity": "{\"sentence_length\": 8, \"unique_words\": 8, \"avg_word_length\": 3.625, \"grammar_complexity\": 0}",
  "Unnamed: 0": 234,
  "joke": "4 ways to become a better risk taker",
  "label": 4
}