{
  "predicted_class": "neutral",
  "confidence_score": 0.9994662404060364,
  "class_probabilities": "{\"self-enhancing\": 0.00011092249769717455, \"self-deprecating\": 9.885212784865871e-05, \"affiliative\": 6.221250805538148e-05, \"aggressive\": 0.0002618335129227489, \"neutral\": 0.9994662404060364}",
  "top_features": "{\"Trump\": -0.002011108705363723, \"picks\": -0.0018766290323426866, \"trading\": -0.0016102561816575226, \"firm\": -0.0013443608287935197, \"secretary\": -0.0012716408664434705}",
  "primary_emotion": "anger   : 0.804",
  "emotion_distribution": "[\"  anger   : 0.804\", \"  joy     : 0.134\", \"  fear    : 0.037\", \"  sadness : 0.014\", \"  love    : 0.009\", \"  surprise: 0.002\"]",
  "dominant_sentiment": "POSITIVE",
  "sentiment_confidence": 0.9931951761245728,
  "sentiment_polarity": -0.2,
  "sentiment_subjectivity": 0.4,
  "sarcasm_probability": 1.0,
  "is_sarcastic": 1,
  "has_contrast": 0,
  "exaggeration_count": 0,
  "intensifier_count": 0,
  "semantic_conflict_count": 7,
  "rhyme_count": 0,
  "has_alliteration": 1,
  "self_reference_count": 0,
  "pun_count": 0,
  "syllable_complexity": 1.5,
  "homonym_count": 2,
  "linguistic_details": "{\"rhymes\": {\"count\": 0, \"pairs\": [], \"found\": false}, \"alliteration\": {\"found\": true, \"groups\": {\"T\": [\"trump\", \"trading\"], \"F\": [\"firm\", \"founder\", \"for\"], \"V\": [\"vincent\", \"viola\"]}}, \"puns\": {\"count\": 0, \"pairs\": [], \"found\": false}, \"syllables\": {\"total\": 15, \"average\": 1.5, \"by_word\": {\"Trump\": 1, \"picks\": 1, \"trading\": 2, \"firm\": 1, \"founder\": 1, \"vincent\": 2, \"viola\": 2, \"for\": 1, \"army\": 1, \"secretary\": 3}}, \"homonyms\": {\"count\": 2, \"words\": {\"picks\": [\"pyx\", \"pix\"], \"for\": [\"four\", \"fore\"]}, \"found\": true}, \"self_reference\": {\"count\": 0, \"instances\": [], \"found\": false}, \"pos_distribution\": {\"NN\": 7, \"IN\": 1, \"NNS\": 1, \"VBG\": 1}}",
  "detailed_analysis": "{\"linguistic_full\": {\"rhyme_pairs\": [], \"alliteration\": {\"T\": [\"trump\", \"trading\"], \"F\": [\"firm\", \"founder\", \"for\"], \"V\": [\"vincent\", \"viola\"]}, \"puns\": [], \"homonyms\": {\"picks\": [\"pyx\", \"pix\"], \"for\": [\"four\", \"fore\"]}, \"syllable_count\": {\"Trump\": 1, \"picks\": 1, \"trading\": 2, \"firm\": 1, \"founder\": 1, \"vincent\": 2, \"viola\": 2, \"for\": 1, \"army\": 1, \"secretary\": 3}, \"self_reference\": [0, []], \"synset_wordnet\": {\"Trump\": \"{'horn', 'best', 'cornet', 'trump_card', 'trumpet', 'scoop', 'ruff', 'outdo', 'outflank', 'trump', 'trump_out'}\", \"picks\": \"{'woof', 'choice', 'nibble', 'plunk', 'picking', 'find_fault', 'pick', 'weft', 'piece', 'pickax', 'beak', 'pickaxe', 'foot', 'break_up', 'cream', 'plectrum', 'pluck', 'selection', 'option', 'blame', 'clean', 'filling', 'plectron', 'cull', 'peck'}\", \"trading\": \"{'trade_in', 'swop', 'deal', 'trade', 'sell', 'switch', 'merchandise', 'trading', 'swap'}\", \"firm\": \"{'unbendable', 'unfaltering', 'immobile', 'steadfast', 'solid', 'steady', 'unfluctuating', 'loyal', 'truehearted', 'unwavering', 'strong', 'house', 'business_firm', 'fast', 'tauten', 'stiff', 'steadfastly', 'unwaveringly', 'unshakable', 'firm', 'firmly'}\", \"founder\": \"{'give_way', 'founding_father', 'break', 'fall_flat', 'flop', 'fall_through', 'collapse', 'cave_in', 'give', 'beginner', 'father', 'fall_in', 'laminitis', 'founder'}\", \"vincent\": \"set()\", \"viola\": \"{'viola', 'genus_Viola', 'Viola'}\", \"for\": \"set()\", \"army\": \"{'regular_army', 'army', 'ground_forces', 'US_Army', 'United_States_Army', 'U._S._Army', 'Army', 'USA'}\", \"secretary\": \"{'escritoire', 'writing_table', 'secretarial_assistant', 'secretaire', 'secretary', 'repository'}\"}, \"part_of_speech\": [[\"Trump\", \"NN\"], [\"picks\", \"NNS\"], [\"trading\", \"VBG\"], [\"firm\", \"NN\"], [\"founder\", \"NN\"], [\"vincent\", \"NN\"], [\"viola\", \"NN\"], [\"for\", \"IN\"], [\"army\", \"NN\"], [\"secretary\", \"NN\"]]}, \"semantic_full\": {\"sentence_contrast\": [], \"word_sentiment\": {\"Trump\": 0.017857142857142856, \"picks\": -0.023809523809523808, \"trading\": 0.0, \"firm\": -0.017857142857142856, \"founder\": -0.10714285714285714, \"viola\": 0.0, \"army\": 0.0, \"secretary\": 0.0}, \"exaggerations\": [], \"intensifiers\": [], \"semantic_conflicts\": [[\"Trump\", \"army\"], [\"trading\", \"viola\"], [\"trading\", \"army\"], [\"trading\", \"secretary\"], [\"firm\", \"secretary\"], [\"founder\", \"army\"], [\"army\", \"secretary\"]]}, \"sentiment_full\": {\"dominant_sentiment\": {\"label\": \"POSITIVE\", \"confidence\": 0.9931951761245728}, \"all_sentiments\": {\"NEGATIVE\": 0.007, \"POSITIVE\": 0.993}, \"sentiment_metrics\": {\"polarity\": -0.2, \"strength\": 0.986, \"subjectivity\": 0.4, \"objectivity\": 0.6, \"direction\": \"negative\"}}, \"emotion_full\": [\"  anger   : 0.804\", \"  joy     : 0.134\", \"  fear    : 0.037\", \"  sadness : 0.014\", \"  love    : 0.009\", \"  surprise: 0.002\"], \"sarcasm_full\": {\"sarcasm_probability\": 1.0, \"is_sarcastic\": true}}",
  "humor_mechanisms": "[[\"alliteration\", 3], [\"homonyms\", 2], [\"sarcasm\", 1.0]]",
  "target_analysis": "{\"self_targeted\": false, \"other_targeted\": false, \"situation_targeted\": true}",
  "linguistic_complexity": "{\"sentence_length\": 10, \"unique_words\": 10, \"avg_word_length\": 5.6, \"grammar_complexity\": 0}",
  "Unnamed: 0": 256,
  "joke": "Trump picks trading firm founder vincent viola for army secretary",
  "label": 4
}