{
  "predicted_class": "aggressive",
  "confidence_score": 0.9552822113037109,
  "class_probabilities": "{\"self-enhancing\": 0.02966524288058281, \"self-deprecating\": 0.005192787852138281, \"affiliative\": 0.008872970938682556, \"aggressive\": 0.9552822113037109, \"neutral\": 0.000986722414381802}",
  "top_features": "{\"you\": -0.050697053987779815, \"rain\": -0.036218323870390305, \"brains\": 0.00979609933186675, \"be\": 0.009428780686328696, \"a\": 0.008376253751644207}",
  "primary_emotion": "anger   : 0.919",
  "emotion_distribution": "[\"  anger   : 0.919\", \"  joy     : 0.048\", \"  sadness : 0.015\", \"  fear    : 0.015\", \"  love    : 0.002\", \"  surprise: 0.002\"]",
  "dominant_sentiment": "NEGATIVE",
  "sentiment_confidence": 0.995411217212677,
  "sentiment_polarity": 0.0,
  "sentiment_subjectivity": 0.0,
  "sarcasm_probability": 0.0,
  "is_sarcastic": 0,
  "has_contrast": 0,
  "exaggeration_count": 0,
  "intensifier_count": 0,
  "semantic_conflict_count": 0,
  "rhyme_count": 0,
  "has_alliteration": 1,
  "self_reference_count": 0,
  "pun_count": 0,
  "syllable_complexity": 1.0,
  "homonym_count": 6,
  "linguistic_details": "{\"rhymes\": {\"count\": 0, \"pairs\": [], \"found\": false}, \"alliteration\": {\"found\": true, \"groups\": {\"B\": [\"brains\", \"be\"]}}, \"puns\": {\"count\": 0, \"pairs\": [], \"found\": false}, \"syllables\": {\"total\": 11, \"average\": 1.0, \"by_word\": {\"If\": 1, \"brains\": 1, \"were\": 1, \"rain\": 1, \",\": 1, \"you\": 1, \"'d\": 1, \"be\": 1, \"a\": 1, \"desert\": 1, \".\": 1}}, \"homonyms\": {\"count\": 6, \"words\": {\"were\": [\"whir\"], \"rain\": [\"reign\", \"rein\"], \"you\": [\"yew\", \"ewe\"], \"be\": [\"bee\"], \"a\": [\"eh\", \"uh\"], \"desert\": [\"dessert\"]}, \"found\": true}, \"self_reference\": {\"count\": 0, \"instances\": [], \"found\": false}, \"pos_distribution\": {\"VB\": 1, \"DT\": 1, \"MD\": 1, \"VBD\": 1, \"NN\": 2, \"IN\": 1, \"PRP\": 1, \"NNS\": 1}}",
  "detailed_analysis": "{\"linguistic_full\": {\"rhyme_pairs\": [], \"alliteration\": {\"B\": [\"brains\", \"be\"]}, \"puns\": [], \"homonyms\": {\"were\": [\"whir\"], \"rain\": [\"reign\", \"rein\"], \"you\": [\"yew\", \"ewe\"], \"be\": [\"bee\"], \"a\": [\"eh\", \"uh\"], \"desert\": [\"dessert\"]}, \"syllable_count\": {\"If\": 1, \"brains\": 1, \"were\": 1, \"rain\": 1, \",\": 1, \"you\": 1, \"'d\": 1, \"be\": 1, \"a\": 1, \"desert\": 1, \".\": 1}, \"self_reference\": [0, []], \"synset_wordnet\": {\"If\": \"set()\", \"brains\": \"{'mind', 'mentality', 'wit', 'encephalon', 'Einstein', 'psyche', 'mental_capacity', 'nous', 'mastermind', 'brain', 'brainpower', 'head', 'brainiac', 'learning_ability', 'genius'}\", \"were\": \"{'exist', 'make_up', 'personify', 'embody', 'live', 'follow', 'represent', 'constitute', 'equal', 'cost', 'comprise', 'be'}\", \"rain\": \"{'rainwater', 'rain', 'rain_down', 'rainfall', 'pelting'}\", \"youd\": \"set()\", \"be\": \"{'exist', 'make_up', 'personify', 'embody', 'live', 'follow', 'represent', 'constitute', 'glucinium', 'beryllium', 'atomic_number_4', 'equal', 'cost', 'Be', 'comprise', 'be'}\", \"a\": \"{'ampere', 'vitamin_A', 'A', 'deoxyadenosine_monophosphate', 'type_A', 'antiophthalmic_factor', 'a', 'axerophthol', 'amp', 'group_A', 'angstrom_unit', 'adenine', 'angstrom'}\", \"desert\": \"{'desolate', 'defect', 'abandon', 'forsake', 'desert'}\"}, \"part_of_speech\": [[\"If\", \"IN\"], [\"brains\", \"NNS\"], [\"were\", \"VBD\"], [\"rain\", \"NN\"], [\"you\", \"PRP\"], [\"'d\", \"MD\"], [\"be\", \"VB\"], [\"a\", \"DT\"], [\"desert\", \"NN\"]]}, \"semantic_full\": {\"sentence_contrast\": [], \"word_sentiment\": {\"brains\": 0.10714285714285714, \"were\": 0.009615384615384616, \"rain\": -0.03125, \"be\": 0.008928571428571428, \"desert\": -0.15625}, \"exaggerations\": [], \"intensifiers\": [], \"semantic_conflicts\": []}, \"sentiment_full\": {\"dominant_sentiment\": {\"label\": \"NEGATIVE\", \"confidence\": 0.995411217212677}, \"all_sentiments\": {\"NEGATIVE\": 0.995, \"POSITIVE\": 0.005}, \"sentiment_metrics\": {\"polarity\": 0.0, \"strength\": 0.991, \"subjectivity\": 0.0, \"objectivity\": 1.0, \"direction\": \"neutral\"}}, \"emotion_full\": [\"  anger   : 0.919\", \"  joy     : 0.048\", \"  sadness : 0.015\", \"  fear    : 0.015\", \"  love    : 0.002\", \"  surprise: 0.002\"], \"sarcasm_full\": {\"sarcasm_probability\": 0.0, \"is_sarcastic\": false}}",
  "humor_mechanisms": "[[\"alliteration\", 1], [\"homonyms\", 6]]",
  "target_analysis": "{\"self_targeted\": false, \"other_targeted\": true, \"situation_targeted\": false}",
  "linguistic_complexity": "{\"sentence_length\": 11, \"unique_words\": 11, \"avg_word_length\": 2.909090909090909, \"grammar_complexity\": 1}",
  "Unnamed: 0": 273,
  "joke": "If brains were rain, you'd be a desert.",
  "label": 3
}